libname/__init__.py
libname/hello.py
hallooworldgk-0.2.3.dist-info/METADATA
hallooworldgk-0.2.3.dist-info/WHEEL
hallooworldgk-0.2.3.dist-info/entry_points.txt
hallooworldgk-0.2.3.dist-info/top_level.txt
hallooworldgk-0.2.3.dist-info/RECORD
